treeignore/__init__.py
treeignore/cli.py
treeignore-0.5.3.dist-info/licenses/LICENSE
treeignore-0.5.3.dist-info/METADATA
treeignore-0.5.3.dist-info/WHEEL
treeignore-0.5.3.dist-info/entry_points.txt
treeignore-0.5.3.dist-info/top_level.txt
treeignore-0.5.3.dist-info/RECORD
