Metadata-Version: 2.4
Name: treeignore
Version: 0.5.3
Summary: A tree view command-line utility that filters files/folders based on a .gitignore
Author-email: Alexander Warth <alexander.warth@mailbox.org>
License-Expression: MIT
Project-URL: Homepage, https://gitlab.com/CochainComplex/treeignore
Project-URL: Repository, https://gitlab.com/CochainComplex/treeignore
Project-URL: Bug Tracker, https://gitlab.com/CochainComplex/treeignore/-/issues
Project-URL: Author Website, https://warth.ai
Keywords: gitignore,tree,directory,visualization,CLI,AI,LLM
Classifier: Development Status :: 4 - Beta
Classifier: Environment :: Console
Classifier: Intended Audience :: Developers
Classifier: Operating System :: OS Independent
Classifier: Programming Language :: Python :: 3
Classifier: Programming Language :: Python :: 3.6
Classifier: Programming Language :: Python :: 3.7
Classifier: Programming Language :: Python :: 3.8
Classifier: Programming Language :: Python :: 3.9
Classifier: Programming Language :: Python :: 3.10
Classifier: Programming Language :: Python :: 3.11
Classifier: Topic :: Software Development :: Version Control :: Git
Classifier: Topic :: Utilities
Requires-Python: >=3.6
License-File: LICENSE
Requires-Dist: pathspec<1.0.0,>=0.11.0
Provides-Extra: dev
Requires-Dist: black<25.0.0,>=23.0.0; extra == "dev"
Requires-Dist: mypy<2.0.0,>=1.8.0; extra == "dev"
Requires-Dist: pytest<8.0.0,>=7.4.0; extra == "dev"
Requires-Dist: pytest-cov<5.0.0,>=4.1.0; extra == "dev"
Requires-Dist: pylint<3.0.0,>=2.17.0; extra == "dev"
Requires-Dist: isort<6.0.0,>=5.12.0; extra == "dev"
Requires-Dist: flake8<7.0.0,>=6.1.0; extra == "dev"
Requires-Dist: pre-commit<4.0.0,>=3.5.0; extra == "dev"
Dynamic: license-file
